ezpackage/__init__.py
ezpackage/package_manager.py
ezpackage/templates/__init__.py
ezpackage/templates/setup_template.txt
ezpackage-0.1.2.dist-info/LICENSE
ezpackage-0.1.2.dist-info/METADATA
ezpackage-0.1.2.dist-info/WHEEL
ezpackage-0.1.2.dist-info/top_level.txt
ezpackage-0.1.2.dist-info/RECORD
