Metadata-Version: 2.1
Name: ezpackage
Version: 0.1.2
Summary: This is an easy way to write your own package.
Home-page: https://github.com/datanooblol/ezpackage
Author: datanooblol
Author-email: data.noob.lol@gmail.com
License: MIT
Keywords: ['python3','ez']
Classifier: Programming Language :: Python :: 3
Classifier: License :: OSI Approved :: MIT License
Classifier: Operating System :: OS Independent
Requires-Python: >=3.0
License-File: LICENSE
Requires-Dist: twine
